papermodels/__init__.py
papermodels/collectors.py
papermodels/filters.py
papermodels/scales.py
papermodels/datatypes/__init__.py
papermodels/datatypes/annotation.py
papermodels/datatypes/element.py
papermodels/datatypes/exceptions.py
papermodels/datatypes/geometry_graph.py
papermodels/datatypes/joist_models.py
papermodels/geometry/geom_ops.py
papermodels/paper/__init__.py
papermodels/paper/annotations.py
papermodels/paper/dxf.py
papermodels/paper/pdf.py
papermodels/paper/plot.py
papermodels-0.21.0.dist-info/licenses/LICENSE
papermodels-0.21.0.dist-info/WHEEL
papermodels-0.21.0.dist-info/METADATA
papermodels-0.21.0.dist-info/RECORD
