Metadata-Version: 2.4
Name: papermodels
Version: 0.21.0
Summary: Load networks
Author-email: Connor Ferster <connor@structuralpython.com>
License-File: LICENSE
Requires-Dist: shapely >= 2.0.0
Requires-Dist: matplotlib
Requires-Dist: numpy >= 2.0.0
Requires-Dist: pandas >= 2.0.0
Requires-Dist: scikit-spatial >= 8.1.0
Requires-Dist: pikepdf
Requires-Dist: parse
Requires-Dist: colour
Requires-Dist: pytest
Requires-Dist: networkx
Requires-Dist: numpy
Requires-Dist: rich
Requires-Dist: tomli-w
Requires-Dist: ezdxf
Requires-Dist: textalloc>=1.2.1
Requires-Dist: load-distribution>=0.1.7
Requires-Dist: pygraphviz>=1.14 ; extra == "graphviz"
Project-URL: Home, https://github.com/structuralpython/papermodels
Provides-Extra: graphviz
